cbcli.py
setup.py
cbcli.egg-info/PKG-INFO
cbcli.egg-info/SOURCES.txt
cbcli.egg-info/dependency_links.txt
cbcli.egg-info/entry_points.txt
cbcli.egg-info/requires.txt
cbcli.egg-info/top_level.txt