Metadata-Version: 1.1
Name: cbcli
Version: 0.1.2
Summary: An unofficial CLI for the Google Container Builder API
Home-page: https://github.com/ajessup/cb-cli
Author: Andrew Jessup
Author-email: ajessup@gmail.com
License: Apache Software License
Keywords: container builder
Platform: UNKNOWN
Classifier: Development Status :: 3 - Alpha
Classifier: Intended Audience :: Developers
Classifier: Topic :: Software Development :: Build Tools
Classifier: License :: OSI Approved :: Apache Software License
Classifier: Programming Language :: Python :: 2
Classifier: Programming Language :: Python :: 2.7
